healpixml/CNN.py
healpixml/CircSpline.py
healpixml/FoCUS.py
healpixml/GCNN.py
healpixml/Softmax.py
healpixml/Spline1D.py
healpixml/Synthesis.py
healpixml/__init__.py
healpixml/alm.py
healpixml/backend.py
healpixml/backend_tens.py
healpixml/loss_backend_tens.py
healpixml/loss_backend_torch.py
healpixml/scat_cov.py
healpixml/scat_cov1D.py
healpixml/scat_cov2D.py
healpixml/scat_cov_map.py
healpixml/scat_cov_map2D.py
healpixml-1.0.0.dist-info/METADATA
healpixml-1.0.0.dist-info/WHEEL
healpixml-1.0.0.dist-info/top_level.txt
healpixml-1.0.0.dist-info/RECORD
