Metadata-Version: 2.2
Name: HealpixML
Version: 1.0.0
Summary: Package adapted for Machine Learning on the Healpix grid.
Author-email: Jean-Marc DELOUIS <jean.marc.delouis@ifremer.fr>
Maintainer-email: Theo Foulquier <theo.foulquier@ifremer.fr>
License: BSD-3-Clause
Project-URL: Repository, https://github.com/jmdelouis/HealpixML.git
Project-URL: Issues, https://github.com/jmdelouis/HealpixML/issues
Project-URL: Documentation, https://healpixml-documentation.readthedocs.io/en/latest/index.html
Keywords: scattering transform,component separation,denoising
Classifier: Intended Audience :: Science/Research
Classifier: License :: OSI Approved :: MIT License
Classifier: Programming Language :: Python :: 3
Classifier: Programming Language :: Python :: 3.9
Classifier: Programming Language :: Python :: 3.10
Classifier: Programming Language :: Python :: 3.11
Classifier: Programming Language :: Python :: 3.12
Requires-Python: >=3.9
Requires-Dist: imageio
Requires-Dist: imagecodecs
Requires-Dist: matplotlib
Requires-Dist: numpy
Requires-Dist: healpy
Requires-Dist: spherical
